MEDS_EIC_AR/__init__.py
MEDS_EIC_AR/__main__.py
MEDS_EIC_AR/utils.py
MEDS_EIC_AR/configs/README.md
MEDS_EIC_AR/configs/__init__.py
MEDS_EIC_AR/configs/_demo_generate_trajectories.yaml
MEDS_EIC_AR/configs/_demo_pretrain.yaml
MEDS_EIC_AR/configs/_generate_trajectories.yaml
MEDS_EIC_AR/configs/_pretrain.yaml
MEDS_EIC_AR/configs/datamodule/__init__.py
MEDS_EIC_AR/configs/datamodule/default.yaml
MEDS_EIC_AR/configs/datamodule/generate_trajectories.yaml
MEDS_EIC_AR/configs/datamodule/pretrain.yaml
MEDS_EIC_AR/configs/inference/default.yaml
MEDS_EIC_AR/configs/inference/demo.yaml
MEDS_EIC_AR/configs/lightning_module/__init__.py
MEDS_EIC_AR/configs/lightning_module/default.yaml
MEDS_EIC_AR/configs/lightning_module/demo.yaml
MEDS_EIC_AR/configs/lightning_module/large.yaml
MEDS_EIC_AR/configs/lightning_module/medium.yaml
MEDS_EIC_AR/configs/lightning_module/micro.yaml
MEDS_EIC_AR/configs/lightning_module/small.yaml
MEDS_EIC_AR/configs/lightning_module/LR_scheduler/__init__.py
MEDS_EIC_AR/configs/lightning_module/LR_scheduler/get_cosine_schedule_with_warmup.yaml
MEDS_EIC_AR/configs/lightning_module/metrics/__init__.py
MEDS_EIC_AR/configs/lightning_module/metrics/default.yaml
MEDS_EIC_AR/configs/lightning_module/model/__init__.py
MEDS_EIC_AR/configs/lightning_module/model/default.yaml
MEDS_EIC_AR/configs/lightning_module/model/demo.yaml
MEDS_EIC_AR/configs/lightning_module/model/large.yaml
MEDS_EIC_AR/configs/lightning_module/model/medium.yaml
MEDS_EIC_AR/configs/lightning_module/model/micro.yaml
MEDS_EIC_AR/configs/lightning_module/model/small.yaml
MEDS_EIC_AR/configs/lightning_module/optimizer/__init__.py
MEDS_EIC_AR/configs/lightning_module/optimizer/adamw.yaml
MEDS_EIC_AR/configs/trainer/__init__.py
MEDS_EIC_AR/configs/trainer/default.yaml
MEDS_EIC_AR/configs/trainer/demo.yaml
MEDS_EIC_AR/configs/trainer/callbacks/__init__.py
MEDS_EIC_AR/configs/trainer/callbacks/default.yaml
MEDS_EIC_AR/configs/trainer/callbacks/early_stopping.yaml
meds_eic_ar-0.1.11.dist-info/licenses/LICENSE
meds_eic_ar-0.1.11.dist-info/METADATA
meds_eic_ar-0.1.11.dist-info/WHEEL
meds_eic_ar-0.1.11.dist-info/entry_points.txt
meds_eic_ar-0.1.11.dist-info/top_level.txt
meds_eic_ar-0.1.11.dist-info/RECORD
