Metadata-Version: 2.4
Name: MEDS_EIC_AR
Version: 0.1.11
Summary: A simple auto-regressive, 'everything-is-code' style model for MEDS datasets
Author-email: Matthew McDermott <mattmcdermott8@gmail.com>, Nassim Oufattole <noufattole@gmail.com>, Teya Bergamaschi <teyabergamaschi@gmail.com>, Aleksia Kolo <aleksiakolo@gmail.com>
Project-URL: Homepage, https://github.com/mmcdermott/MEDS_EIC_AR
Project-URL: Issues, https://github.com/mmcdermott/MEDS_EIC_AR/issues
Classifier: Programming Language :: Python :: 3
Classifier: License :: OSI Approved :: MIT License
Classifier: Operating System :: OS Independent
Requires-Python: >=3.11
License-File: LICENSE
Requires-Dist: polars~=1.30.0
Requires-Dist: pyarrow
Requires-Dist: hydra-core
Requires-Dist: numpy
Requires-Dist: meds~=0.4.0
Requires-Dist: filelock
Requires-Dist: pytest
Requires-Dist: meds_testing_helpers~=0.3.0
Requires-Dist: MEDS-transforms~=0.5.2
Requires-Dist: meds-torch-data[lightning]~=0.6.3
Requires-Dist: transformers
Requires-Dist: torch
Requires-Dist: torchmetrics
Requires-Dist: lightning~=2.5.1
Requires-Dist: MEDS_trajectory_evaluation~=0.0.3
Provides-Extra: wandb
Requires-Dist: wandb; extra == "wandb"
Provides-Extra: mlflow
Requires-Dist: mlflow; extra == "mlflow"
Requires-Dist: psutil; extra == "mlflow"
Requires-Dist: pynvml; extra == "mlflow"
Provides-Extra: dev
Requires-Dist: pre-commit<4; extra == "dev"
Requires-Dist: ruff; extra == "dev"
Provides-Extra: tests
Requires-Dist: pytest-cov; extra == "tests"
Requires-Dist: pretty_print_directory>=0.1.2; extra == "tests"
Requires-Dist: yaml_to_disk; extra == "tests"
Dynamic: license-file
